wszst_yaz0_c.cp37-win_amd64.pyd
wszst_yaz0_c-1.0.1.dist-info/METADATA
wszst_yaz0_c-1.0.1.dist-info/WHEEL
wszst_yaz0_c-1.0.1.dist-info/top_level.txt
wszst_yaz0_c-1.0.1.dist-info/RECORD
