Metadata-Version: 2.1
Name: wszst-yaz0-c
Version: 1.0.1
Summary: Native extension for wszst_yaz0
Home-page: UNKNOWN
Author: leoetlino
Author-email: leo@leolam.fr
License: UNKNOWN
Platform: UNKNOWN
